functino/__init__.py
functino/execute.py
functino/file.py
functino/language.py
functino/platform_path.py
functino/project_path.py
functino/gui/__init__.py
functino/gui/editor.py
functino/gui/exception.py
functino/gui/icon.py
functino/gui/language.py
functino/gui/theme.py
functino/gui/window.py
functino/resources/icons/play_dark.svg
functino/resources/icons/play_light.svg
functino/resources/icons/settings_dark.svg
functino/resources/icons/settings_light.svg
functino/resources/language_profiles/c_gcc.toml
functino/resources/language_profiles/cpp_gcc.toml
functino/resources/language_profiles/nodejs.toml
functino/resources/language_profiles/python.toml
functino/resources/language_profiles/ruby.toml
functino/resources/language_profiles/rust.toml
functino/resources/themes/LICENSE
functino/resources/themes/README.md
functino/resources/themes/dark.xml
functino/resources/themes/light.xml
functino-0.0.3.dist-info/LICENSE
functino-0.0.3.dist-info/METADATA
functino-0.0.3.dist-info/WHEEL
functino-0.0.3.dist-info/entry_points.txt
functino-0.0.3.dist-info/top_level.txt
functino-0.0.3.dist-info/RECORD
