Metadata-Version: 2.1
Name: functino
Version: 0.0.3
Summary: Simple graphical code editor and runner for throwaway code
Author-email: David Scholberg <recombinant.vector@gmail.com>
License: BSD-2-Clause license
Project-URL: Source Code, https://github.com/davidscholberg/functino
Keywords: text editor,coding,software development,gui,qt,scintilla,c,c++,javascript,nodejs,python,ruby,rust
Classifier: Development Status :: 4 - Beta
Classifier: Intended Audience :: Developers
Classifier: Intended Audience :: End Users/Desktop
Classifier: License :: OSI Approved :: BSD License
Classifier: Natural Language :: English
Classifier: Operating System :: OS Independent
Classifier: Programming Language :: C
Classifier: Programming Language :: C++
Classifier: Programming Language :: JavaScript
Classifier: Programming Language :: Python
Classifier: Programming Language :: Python :: 3
Classifier: Programming Language :: Python :: 3 :: Only
Classifier: Programming Language :: Python :: 3.11
Classifier: Programming Language :: Ruby
Classifier: Programming Language :: Rust
Classifier: Topic :: Software Development
Classifier: Topic :: Text Editors
Requires-Python: >=3.11
License-File: LICENSE
Requires-Dist: PyQt6
Requires-Dist: PyQt6-QScintilla
Provides-Extra: dev
Requires-Dist: black ; extra == 'dev'
Requires-Dist: docformatter ; extra == 'dev'
Requires-Dist: flake8 ; extra == 'dev'
Requires-Dist: pre-commit ; extra == 'dev'
Requires-Dist: pyinstaller ; extra == 'dev'
